tc2_hw/__init__.py
tc2_hw/cli.py
tc2_hw/tc2_hw.py
tc2_hw-0.1.0.dist-info/AUTHORS.rst
tc2_hw-0.1.0.dist-info/LICENSE
tc2_hw-0.1.0.dist-info/METADATA
tc2_hw-0.1.0.dist-info/WHEEL
tc2_hw-0.1.0.dist-info/entry_points.txt
tc2_hw-0.1.0.dist-info/top_level.txt
tc2_hw-0.1.0.dist-info/RECORD
