Metadata-Version: 2.1
Name: tc2-hw
Version: 0.1.0
Summary: Python Boilerplate contains all the boilerplate you need to create a Python package.
Home-page: https://github.com/audreyr/tc2_hw
Author: Mark Laszlo
Author-email: mark@tc2.hu
License: MIT license
Keywords: tc2_hw
Platform: UNKNOWN
Classifier: Development Status :: 2 - Pre-Alpha
Classifier: Intended Audience :: Developers
Classifier: License :: OSI Approved :: MIT License
Classifier: Natural Language :: English
Classifier: Programming Language :: Python :: 3
Classifier: Programming Language :: Python :: 3.5
Classifier: Programming Language :: Python :: 3.6
Classifier: Programming Language :: Python :: 3.7
Classifier: Programming Language :: Python :: 3.8
Requires-Python: >=3.5
Requires-Dist: Click (>=7.0)
